pulumi_dnsimple/__init__.py
pulumi_dnsimple/_enums.py
pulumi_dnsimple/_inputs.py
pulumi_dnsimple/_utilities.py
pulumi_dnsimple/contact.py
pulumi_dnsimple/domain.py
pulumi_dnsimple/domain_delegation.py
pulumi_dnsimple/ds_record.py
pulumi_dnsimple/email_forward.py
pulumi_dnsimple/get_certificate.py
pulumi_dnsimple/get_registrant_change_check.py
pulumi_dnsimple/get_zone.py
pulumi_dnsimple/lets_encrypt_certificate.py
pulumi_dnsimple/outputs.py
pulumi_dnsimple/provider.py
pulumi_dnsimple/pulumi-plugin.json
pulumi_dnsimple/py.typed
pulumi_dnsimple/registered_domain.py
pulumi_dnsimple/zone.py
pulumi_dnsimple/zone_record.py
pulumi_dnsimple/config/__init__.py
pulumi_dnsimple/config/__init__.pyi
pulumi_dnsimple/config/vars.py
pulumi_dnsimple-5.0.0.dist-info/METADATA
pulumi_dnsimple-5.0.0.dist-info/WHEEL
pulumi_dnsimple-5.0.0.dist-info/top_level.txt
pulumi_dnsimple-5.0.0.dist-info/RECORD
